rtamt/__init__.py
rtamt/antlr/__init__.py
rtamt/antlr/parser/__init__.py
rtamt/antlr/parser/ltl/LtlLexer.py
rtamt/antlr/parser/ltl/LtlParser.py
rtamt/antlr/parser/ltl/LtlParserVisitor.py
rtamt/antlr/parser/ltl/__init__.py
rtamt/antlr/parser/ltl/error/__init__.py
rtamt/antlr/parser/ltl/error/parser_error_listener.py
rtamt/antlr/parser/stl/StlLexer.py
rtamt/antlr/parser/stl/StlParser.py
rtamt/antlr/parser/stl/StlParserVisitor.py
rtamt/antlr/parser/stl/__init__.py
rtamt/antlr/parser/stl/error/__init__.py
rtamt/antlr/parser/stl/error/parser_error_listener.py
rtamt/exception/__init__.py
rtamt/exception/exception.py
rtamt/lib/__init__.py
rtamt/lib/rtamt_stl_library_wrapper/__init__.py
rtamt/pastifier/__init__.py
rtamt/pastifier/ltl/__init__.py
rtamt/pastifier/ltl/horizon.py
rtamt/pastifier/ltl/pastifier.py
rtamt/pastifier/stl/__init__.py
rtamt/pastifier/stl/horizon.py
rtamt/pastifier/stl/pastifier.py
rtamt/semantics/__init__.py
rtamt/semantics/abstract_dense_time_offline_interpreter.py
rtamt/semantics/abstract_dense_time_online_interpreter.py
rtamt/semantics/abstract_dense_time_online_operation.py
rtamt/semantics/abstract_discrete_time_offline_interpreter.py
rtamt/semantics/abstract_discrete_time_online_interpreter.py
rtamt/semantics/abstract_interpreter.py
rtamt/semantics/abstract_offline_interpreter.py
rtamt/semantics/abstract_online_interpreter.py
rtamt/semantics/abstract_online_operation.py
rtamt/semantics/dense_time_interpreter.py
rtamt/semantics/discrete_time_interpreter.py
rtamt/semantics/sample.py
rtamt/semantics/time_interpreter.py
rtamt/semantics/arithmetic/__init__.py
rtamt/semantics/arithmetic/dense_time/__init__.py
rtamt/semantics/arithmetic/dense_time/online/__init__.py
rtamt/semantics/arithmetic/dense_time/online/abs_operation.py
rtamt/semantics/arithmetic/dense_time/online/addition_operation.py
rtamt/semantics/arithmetic/dense_time/online/division_operation.py
rtamt/semantics/arithmetic/dense_time/online/exp_operation.py
rtamt-0.3.5.dist-info/LICENSE
rtamt-0.3.5.dist-info/METADATA
rtamt-0.3.5.dist-info/WHEEL
rtamt-0.3.5.dist-info/top_level.txt
rtamt-0.3.5.dist-info/RECORD
